ykenan_fragments/__init__.py
ykenan_fragments/model/__init__.py
ykenan_fragments/util/__init__.py
ykenan_fragments-1.2.18.dist-info/LICENSE
ykenan_fragments-1.2.18.dist-info/METADATA
ykenan_fragments-1.2.18.dist-info/WHEEL
ykenan_fragments-1.2.18.dist-info/top_level.txt
ykenan_fragments-1.2.18.dist-info/RECORD
