Metadata-Version: 2.1
Name: ykenan_fragments
Version: 1.2.18
Summary: Forming fragments files through three files (barcodes.txt.gz, .mtx.gz and .peaks.txt)
Author-email: Yu Zhengmin <3236170161@qq.com>
Project-URL: github, https://github.com/YuZhengM/ykenan_fragments
Keywords: ykenan,fragments
Classifier: Programming Language :: Python :: 3
Classifier: License :: OSI Approved :: MIT License
Classifier: Operating System :: OS Independent
Requires-Python: >=3.9
License-File: LICENSE
Requires-Dist: ykenan-file >=0.2.3
Requires-Dist: pandas >=1.5.3
